cc_plugin_glider/__init__.py
cc_plugin_glider/_version.py
cc_plugin_glider/glider_dac.py
cc_plugin_glider/required_var_attrs.py
cc_plugin_glider/util.py
cc_plugin_glider/tests/__init__.py
cc_plugin_glider/tests/resources.py
cc_plugin_glider/tests/test_glidercheck.py
cc_plugin_glider/tests/data/Bad.cdl
cc_plugin_glider/tests/data/IOOS_Glider_NetCDF_v2.0.cdl
cc_plugin_glider/tests/data/IOOS_Glider_NetCDF_v3.0.cdl
cc_plugin_glider/tests/data/bad_location.cdl
cc_plugin_glider/tests/data/bad_metadata.cdl
cc_plugin_glider/tests/data/bad_qc.cdl
cc_plugin_glider/tests/data/bad_standard_name.cdl
cc_plugin_glider/tests/data/bad_units.cdl
cc_plugin_glider/tests/data/ncei_metadata.xml
cc_plugin_glider/tests/data/no_qc.cdl
cc_plugin_glider/tests/data/seanames.xml
cc_plugin_glider-2.1.0.dist-info/licenses/LICENSE.txt
cc_plugin_glider-2.1.0.dist-info/METADATA
cc_plugin_glider-2.1.0.dist-info/WHEEL
cc_plugin_glider-2.1.0.dist-info/entry_points.txt
cc_plugin_glider-2.1.0.dist-info/top_level.txt
cc_plugin_glider-2.1.0.dist-info/RECORD
