Metadata-Version: 2.4
Name: cc-plugin-glider
Version: 2.1.0
Summary: Compliance Checker Glider DAC plugin
Maintainer-email: Benjamin Adams <benjamin.adams@tetratech.com>
License: Apache-2.0
Project-URL: documentation, http://ioos.github.io/compliance-checker/
Project-URL: homepage, https://github.com/ioos/cc-plugin-glider
Project-URL: repository, https://github.com/ioos/cc-plugin-glider
Classifier: Programming Language :: Python :: 3 :: Only
Classifier: Programming Language :: Python :: 3.9
Classifier: Programming Language :: Python :: 3.10
Classifier: Programming Language :: Python :: 3.11
Classifier: Programming Language :: Python :: 3.12
Classifier: Programming Language :: Python :: 3.13
Classifier: Programming Language :: Python :: 3.14
Requires-Python: >=3.9
License-File: LICENSE.txt
Requires-Dist: compliance-checker>=4.3.2
Dynamic: license-file
